splive/__init__.py
splive/__main__.py
splive/splive.py
splive-0.0.4.dist-info/LICENSE
splive-0.0.4.dist-info/METADATA
splive-0.0.4.dist-info/WHEEL
splive-0.0.4.dist-info/entry_points.txt
splive-0.0.4.dist-info/top_level.txt
splive-0.0.4.dist-info/RECORD
