Metadata-Version: 2.1
Name: splive
Version: 0.0.4
Summary: Lightweight CSV splicer / merger
Home-page: https://github.com/chrismettal/splive
Author: Chrismettal
Author-email: chrismettal@binary-6.de
Project-URL: Bug Tracker, https://github.com/Chrismettal/Splive/issues
Classifier: Programming Language :: Python :: 3
Classifier: License :: OSI Approved :: GNU General Public License v3 or later (GPLv3+)
Classifier: Operating System :: OS Independent
Requires-Python: >=3.6
License-File: LICENSE
